aesthetics_predictor/__init__.py
aesthetics_predictor/utils.py
aesthetics_predictor/v1.py
aesthetics_predictor/v2.py
simple_aesthetics_predictor-0.1.2.dist-info/LICENSE
simple_aesthetics_predictor-0.1.2.dist-info/METADATA
simple_aesthetics_predictor-0.1.2.dist-info/WHEEL
simple_aesthetics_predictor-0.1.2.dist-info/RECORD
