Metadata-Version: 2.1
Name: simple-aesthetics-predictor
Version: 0.1.2
Summary: 
Author: Shunsuke KITADA
Author-email: shunsuke.kitada.0831@gmail.com
Requires-Python: >=3.8,<4.0
Classifier: Programming Language :: Python :: 3
Classifier: Programming Language :: Python :: 3.8
Classifier: Programming Language :: Python :: 3.9
Classifier: Programming Language :: Python :: 3.10
Classifier: Programming Language :: Python :: 3.11
Requires-Dist: torch (>=1.0)
Requires-Dist: torchvision (>=0.2.1)
Requires-Dist: transformers (>=4.30.2,<5.0.0)
